duckstruct/__init__.py
duckstruct/abstract.py
duckstruct/typesearch.py
duckstruct-0.0.1.dist-info/METADATA
duckstruct-0.0.1.dist-info/WHEEL
duckstruct-0.0.1.dist-info/top_level.txt
duckstruct-0.0.1.dist-info/RECORD
