Metadata-Version: 2.1
Name: duckstruct
Version: 0.0.1
Summary: Extracting data structures from runtime duck typing.
Home-page: https://github.com/maniospas/duckstruct
Author: Emmanouil Krasanakis
Author-email: maniospas@hotmail.com
License: Apache 2.0
Keywords: duck typing,data types
Platform: UNKNOWN
Classifier: Development Status :: 1 - Planning
Classifier: Programming Language :: Python :: 3
Classifier: License :: OSI Approved :: Apache Software License
Classifier: Operating System :: OS Independent
